xwavecal/__init__.py
xwavecal/basic.py
xwavecal/blaze.py
xwavecal/database.py
xwavecal/extract.py
xwavecal/fibers.py
xwavecal/images.py
xwavecal/main.py
xwavecal/munge.py
xwavecal/stages.py
xwavecal/traces.py
xwavecal/variance.py
xwavecal/wavelength.py
xwavecal/data/.logging.ini
xwavecal/tests/__init__.py
xwavecal/tests/test_basic.py
xwavecal/tests/test_blaze.py
xwavecal/tests/test_correlate.py
xwavecal/tests/test_database.py
xwavecal/tests/test_e2e.py
xwavecal/tests/test_extract.py
xwavecal/tests/test_fibers.py
xwavecal/tests/test_fits_utils.py
xwavecal/tests/test_image.py
xwavecal/tests/test_main.py
xwavecal/tests/test_misc_utils.py
xwavecal/tests/test_munge.py
xwavecal/tests/test_overlap_utils.py
xwavecal/tests/test_runtime_utils.py
xwavecal/tests/test_traces.py
xwavecal/tests/test_variance.py
xwavecal/tests/test_wavelength.py
xwavecal/tests/utils.py
xwavecal/utils/__init__.py
xwavecal/utils/basic_utils.py
xwavecal/utils/blaze_utils.py
xwavecal/utils/correlate.py
xwavecal/utils/extract_utils.py
xwavecal/utils/fiber_utils.py
xwavecal/utils/fits_utils.py
xwavecal/utils/instrument_specific.py
xwavecal/utils/misc_utils.py
xwavecal/utils/overlap_utils.py
xwavecal/utils/runtime_utils.py
xwavecal/utils/trace_utils.py
xwavecal/utils/wavelength_utils.py
xwavecal-0.1.13.dist-info/LICENSE
xwavecal-0.1.13.dist-info/METADATA
xwavecal-0.1.13.dist-info/WHEEL
xwavecal-0.1.13.dist-info/entry_points.txt
xwavecal-0.1.13.dist-info/top_level.txt
xwavecal-0.1.13.dist-info/RECORD
