Metadata-Version: 2.1
Name: xwavecal
Version: 0.1.13
Summary: UNKNOWN
Home-page: https://github.com/gmbrandt/xwavecal
Author: G. Mirek Brandt, Curtis McCully, Timothy Brandt
Author-email: gmbrandt@ucsb.edu
License: UNKNOWN
Platform: UNKNOWN
Requires-Python: >=3.6
Requires-Dist: astropy (>=4.0)
Requires-Dist: scipy (>=1.3.2)
Requires-Dist: numpy (>=1.16)
